file_typer/__init__.py
file_typer/__main__.py
file_typer/argutils.py
file_typer/impl.py
file_typer/type_table.py
file_typer-1.0.19.dist-info/LICENSE
file_typer-1.0.19.dist-info/METADATA
file_typer-1.0.19.dist-info/WHEEL
file_typer-1.0.19.dist-info/entry_points.txt
file_typer-1.0.19.dist-info/top_level.txt
file_typer-1.0.19.dist-info/RECORD
